[
  {"id": 0, "productURL": "opus-1", "title": "Opus 1", "text": "sdbhjhvsv"},
  {"id": 1, "productURL": "opus-2", "title": "Opus 2", "text": "fsdgfdgd"},
  {"id": 2, "productURL": "opus-3", "title": "Opus 3", "text": "nunfas"},
  {"id": 3, "productURL": "opus-4", "title": "Opus 4", "text": "sdf"},
  {"id": 4, "productURL": "opus-5", "title": "Opus 5", "text": "nunfas"},
  {"id": 5, "productURL": "opus-6", "title": "Opus 6", "text": "nunfas"},
  {"id": 6, "productURL": "opus-7", "title": "Opus 7", "text": "nunfas"},
  {"id": 7, "productURL": "opus-8", "title": "Opus 8", "text": "nunfas"},
  {"id": 8, "productURL": "opus-9", "title": "Opus 9", "text": "nunfas"}
]